odoo10_addon_asterisk_click2dial-10.0.1.0.0.99.dev15-py3.8-nspkg.pth
odoo/addons/asterisk_click2dial/__init__.py
odoo/addons/asterisk_click2dial/__manifest__.py
odoo/addons/asterisk_click2dial/controller.py
odoo/addons/asterisk_click2dial/requirements.txt
odoo/addons/asterisk_click2dial/web_asterisk_click2dial.xml
odoo/addons/asterisk_click2dial/demo/asterisk_click2dial_demo.xml
odoo/addons/asterisk_click2dial/i18n/am.po
odoo/addons/asterisk_click2dial/i18n/asterisk_click2dial.pot
odoo/addons/asterisk_click2dial/i18n/bg.po
odoo/addons/asterisk_click2dial/i18n/ca.po
odoo/addons/asterisk_click2dial/i18n/de.po
odoo/addons/asterisk_click2dial/i18n/el_GR.po
odoo/addons/asterisk_click2dial/i18n/es.po
odoo/addons/asterisk_click2dial/i18n/es_ES.po
odoo/addons/asterisk_click2dial/i18n/fi.po
odoo/addons/asterisk_click2dial/i18n/fr.po
odoo/addons/asterisk_click2dial/i18n/gl.po
odoo/addons/asterisk_click2dial/i18n/hr.po
odoo/addons/asterisk_click2dial/i18n/it.po
odoo/addons/asterisk_click2dial/i18n/pt.po
odoo/addons/asterisk_click2dial/i18n/pt_BR.po
odoo/addons/asterisk_click2dial/i18n/pt_PT.po
odoo/addons/asterisk_click2dial/i18n/sl.po
odoo/addons/asterisk_click2dial/i18n/tr.po
odoo/addons/asterisk_click2dial/models/__init__.py
odoo/addons/asterisk_click2dial/models/asterisk_server.py
odoo/addons/asterisk_click2dial/models/phone_common.py
odoo/addons/asterisk_click2dial/models/res_users.py
odoo/addons/asterisk_click2dial/scripts/odoo_popup_timeout.sh
odoo/addons/asterisk_click2dial/scripts/set_name_agi.py
odoo/addons/asterisk_click2dial/scripts/set_name_incoming_timeout.sh
odoo/addons/asterisk_click2dial/scripts/set_name_outgoing_timeout.sh
odoo/addons/asterisk_click2dial/security/ir.model.access.csv
odoo/addons/asterisk_click2dial/static/description/icon.png
odoo/addons/asterisk_click2dial/static/description/sshot-click2dial.jpg
odoo/addons/asterisk_click2dial/static/description/sshot-open_calling_party.jpg
odoo10_addon_asterisk_click2dial-10.0.1.0.0.99.dev15.dist-info/METADATA
odoo10_addon_asterisk_click2dial-10.0.1.0.0.99.dev15.dist-info/WHEEL
odoo10_addon_asterisk_click2dial-10.0.1.0.0.99.dev15.dist-info/namespace_packages.txt
odoo10_addon_asterisk_click2dial-10.0.1.0.0.99.dev15.dist-info/top_level.txt
odoo10_addon_asterisk_click2dial-10.0.1.0.0.99.dev15.dist-info/RECORD
